fire_app/__init__.py
fire_app/main.py
fire_app-0.1.0.dist-info/licenses/LICENSE
fire_app-0.1.0.dist-info/METADATA
fire_app-0.1.0.dist-info/WHEEL
fire_app-0.1.0.dist-info/entry_points.txt
fire_app-0.1.0.dist-info/top_level.txt
fire_app-0.1.0.dist-info/RECORD
