Metadata-Version: 2.4
Name: fire-app
Version: 0.1.0
Summary: A modern performance finance tracker built with PySide6
Author-email: Ismael Jimenez <ismael@example.com>
License: MIT
Project-URL: Homepage, https://github.com/ijimenez/fire-app
Project-URL: Repository, https://github.com/ijimenez/fire-app.git
Project-URL: Issues, https://github.com/ijimenez/fire-app/issues
Keywords: finance,tracker,gui,pyside6,investment,portfolio
Classifier: Development Status :: 3 - Alpha
Classifier: Intended Audience :: End Users/Desktop
Classifier: License :: OSI Approved :: MIT License
Classifier: Operating System :: OS Independent
Classifier: Programming Language :: Python :: 3
Classifier: Programming Language :: Python :: 3.8
Classifier: Programming Language :: Python :: 3.9
Classifier: Programming Language :: Python :: 3.10
Classifier: Programming Language :: Python :: 3.11
Classifier: Programming Language :: Python :: 3.12
Classifier: Topic :: Office/Business :: Financial
Classifier: Topic :: Office/Business :: Financial :: Investment
Requires-Python: >=3.8
License-File: LICENSE
Requires-Dist: PySide6>=6.5.0
Provides-Extra: dev
Requires-Dist: pytest>=6.0; extra == "dev"
Requires-Dist: pytest-qt>=4.0; extra == "dev"
Requires-Dist: black>=22.0; extra == "dev"
Requires-Dist: isort>=5.0; extra == "dev"
Requires-Dist: flake8>=4.0; extra == "dev"
Dynamic: license-file
